MANIFEST.in
README.md
mkdocs.yml
setup.cfg
setup.py
docs/README.html
docs/README.md
docs/README.md.bak
docs/pypi.txt
docs/trash.md
site/__init__.py
test/conftest.py
test/test_simple/config.yml
test/test_simple/test_my_app.py
test/test_simple/test_my_app.yml
test/test_simple/test_my_app_ams1.out
test/test_simple/test_my_app_ams2.out
test/test_typical/config.yml
test/test_typical/test_cmdline.py
test/test_typical/test_cmdline.yml
test/test_typical/test_cmdline_args1.out
test/test_typical/test_cmdline_args2.out
yaop.egg-info/PKG-INFO
yaop.egg-info/SOURCES.txt
yaop.egg-info/dependency_links.txt
yaop.egg-info/not-zip-safe
yaop.egg-info/requires.txt
yaop.egg-info/top_level.txt