Metadata-Version: 1.1
Name: yaop
Version: 0.1.1
Summary: Yet Another Option Parser (full fledged)
Home-page: https://github.com/Aygos/yaop
Author: Aygos (C.B.)
Author-email: cyrilb02@sfr.fr
License: Creative Commons - BY-NC-ND
Keywords: yaop command line optparse config file YAML resource banner help script application console shell
Platform: UNKNOWN
Classifier: Development Status :: 2 - Pre-Alpha
Classifier: Environment :: Console
Classifier: Framework :: Pytest
Classifier: Intended Audience :: Developers
Classifier: Natural Language :: English
Classifier: Natural Language :: French
Classifier: Operating System :: OS Independent
Classifier: Programming Language :: Python :: 2.7
Classifier: Topic :: Software Development :: Interpreters
Classifier: Topic :: Software Development :: Libraries
Classifier: Topic :: Text Processing :: Linguistic
Classifier: Topic :: System :: Shells
Classifier: Topic :: Text Processing
